server/__init__.py
server/server_.py
server/common/__init__.py
server/common/decos.py
server/common/descryptors.py
server/common/errors.py
server/common/metaclasses.py
server/common/utils.py
server/common/variables.py
server/logs/__init__.py
server/logs/config_client_log.py
server/logs/config_server_log.py
server/server/__init__.py
server/server/add_user.py
server/server/config_window.py
server/server/core.py
server/server/database.py
server/server/main_window.py
server/server/remove_user.py
server/server/stat_window.py
server/unit_tests/__init__.py
message_server_svg-0.8.7.dist-info/METADATA
message_server_svg-0.8.7.dist-info/WHEEL
message_server_svg-0.8.7.dist-info/top_level.txt
message_server_svg-0.8.7.dist-info/RECORD
