Metadata-Version: 2.1
Name: message-server-svg
Version: 0.8.7
Summary: message_server
Author: Sergey Grishin
Author-email: svg95@lsit.ru
Requires-Dist: PyQt5
Requires-Dist: sqlalchemy
Requires-Dist: pycryptodome
Requires-Dist: pycryptodomex
